manage.py
medux/asgi.py
medux/settings.py
medux/urls.py
medux/utils.py
medux/views.py
medux/wsgi.py
medux/common/__init__.py
medux/common/admin.py
medux/common/apps.py
medux/common/bootstrap.py
medux/common/conf.py
medux/common/constants.py
medux/common/context_processors.py
medux/common/menu.py
medux/common/menus.py
medux/common/middleware.py
medux/common/mixins.py
medux/common/models.py
medux/common/signals.py
medux/common/tools.py
medux/common/urls.py
medux/common/validators.py
medux/common/widgets.py
medux/common/api/__init__.py
medux/common/api/interfaces.py
medux/common/api/http/__init__.py
medux/common/auth/__init__.py
medux/common/auth/forms.py
medux/common/forms/__init__.py
medux/common/forms/mixins.py
medux/common/forms/user.py
medux/common/forms/widgets.py
medux/common/htmx/__init__.py
medux/common/htmx/mixins.py
medux/common/management/__init__.py
medux/common/management/commands/__init__.py
medux/common/management/commands/initialize.py
medux/common/management/commands/loadpreferences.py
medux/common/management/commands/update_libraries.py
medux/common/migrations/0001_initial.py
medux/common/migrations/0002_initial.py
medux/common/migrations/0003_delete_notification.py
medux/common/migrations/0004_alter_commonuser_options_commonuser_color.py
medux/common/migrations/__init__.py
medux/common/templatetags/__init__.py
medux/common/templatetags/breadcrumbs.py
medux/common/templatetags/medux.py
medux/common/tests/__init__.py
medux/common/tests/test_group_permissions.py
medux/common/tests/test_loader.py
medux/common/tests/test_tools.py
medux/common/views/__init__.py
medux/common/views/multiple.py
medux/contrib/__init__.py
medux/core/__init__.py
medux/core/admin.py
medux/core/apps.py
medux/core/conf.py
medux/core/datapacks.py
medux/core/fields.py
medux/core/forms.py
medux/core/menus.py
medux/core/middleware.py
medux/core/schema.py
medux/core/serializers(not used).py
medux/core/signals.py
medux/core/urls.py
medux/core/validators.py
medux/core/api/__init__.py
medux-0.0.6.dist-info/LICENSE.md
medux-0.0.6.dist-info/METADATA
medux-0.0.6.dist-info/WHEEL
medux-0.0.6.dist-info/top_level.txt
medux-0.0.6.dist-info/RECORD
