Metadata-Version: 2.1
Name: medux
Version: 0.0.6
Summary: MedUX: Open Source Electronic Medical Record
Author-email: Christian González <office@nerdocs.at>
License: ### GNU AFFERO GENERAL PUBLIC LICENSE
Project-URL: Home, https://medux.readthedocs.org
Project-URL: Source, https://gitlab.com/nerdocs/medux/medux
Project-URL: Documentation, https://medux.readthedocs.org
Project-URL: Tracker, https://gitlab.com/nerdocs/medux/medux/issues
Classifier: Development Status :: 2 - Pre-Alpha
Classifier: Environment :: Web Environment
Classifier: Framework :: Django :: 4.1
Classifier: Intended Audience :: Developers
Classifier: License :: OSI Approved :: GNU Affero General Public License v3 or later (AGPLv3+)
Classifier: Natural Language :: English
Classifier: Operating System :: OS Independent
Classifier: Topic :: Internet :: WWW/HTTP
Classifier: Topic :: Internet :: WWW/HTTP :: Dynamic Content
Requires-Python: >=3.10
License-File: LICENSE.md
Requires-Dist: medux-common
Provides-Extra: deploy
Requires-Dist: channels-redis ; extra == 'deploy'
Provides-Extra: dev
Requires-Dist: black ; extra == 'dev'
Requires-Dist: pytest (~=6.2.5) ; extra == 'dev'
Requires-Dist: pytest-django ; extra == 'dev'
Requires-Dist: pytest-cov ; extra == 'dev'
Requires-Dist: flake8 ; extra == 'dev'
Requires-Dist: pre-commit ; extra == 'dev'
Requires-Dist: django-extensions ; extra == 'dev'
Requires-Dist: django-debug-toolbar ; extra == 'dev'
Requires-Dist: django-sass ; extra == 'dev'
Requires-Dist: cryptography ; extra == 'dev'
Requires-Dist: cookiecutter ; extra == 'dev'
Requires-Dist: gitpython ; extra == 'dev'
Provides-Extra: doc
Requires-Dist: mkdocs ; extra == 'doc'
Requires-Dist: mkdocstrings[python] ; extra == 'doc'
Requires-Dist: mkdocs-material ; extra == 'doc'
